datainsightx/__init__.py
datainsightx/core.py
datainsightx-1.0.1.dist-info/licenses/LICENSE
datainsightx-1.0.1.dist-info/METADATA
datainsightx-1.0.1.dist-info/WHEEL
datainsightx-1.0.1.dist-info/top_level.txt
datainsightx-1.0.1.dist-info/RECORD
